[
  {
    "Course Section": "CPSC_V 310-L2C - Introduction to Software Engineering",
    "Instructional Format": "Laboratory",
    "Section Status": "Open",
    "Delivery Mode": "In Person Learning",
    "zCF - CT - Maximum Credits": "4 Credits",
    "zCF - CT - Enrolled/Capacity": "Enrolled/Capacity: 28/31",
    "Section Details": "Wed | 10:00 a.m. - 12:00 p.m. | 2025-01-08 - 2025-02-12",
    "Drop and Withdrawal Deadlines": "Drop: 2025/01/17\nWithdrawal: 2025/03/07"
  },
  {
    "Course Section": "CPSC_V 310-L2D - Introduction to Software Engineering",
    "Instructional Format": "Laboratory",
    "Section Status": "Open",
    "Delivery Mode": "In Person Learning",
    "zCF - CT - Maximum Credits": "4 Credits",
    "zCF - CT - Enrolled/Capacity": "Enrolled/Capacity: 29/31",
    "Section Details": "Fri | 3:00 p.m. - 5:00 p.m. | 2025-01-10 - 2025-02-14",
    "Drop and Withdrawal Deadlines": "Drop: 2025/01/17\nWithdrawal: 2025/03/07"
  },
  {
    "Course Section": "CPSC_V 310-L2E - Introduction to Software Engineering",
    "Instructional Format": "Laboratory",
    "Section Status": "Open",
    "Delivery Mode": "In Person Learning",
    "zCF - CT - Maximum Credits": "4 Credits",
    "zCF - CT - Enrolled/Capacity": "Enrolled/Capacity: 29/31",
    "Section Details": "Wed | 4:00 p.m. - 6:00 p.m. | 2025-01-08 - 2025-02-12",
    "Drop and Withdrawal Deadlines": "Drop: 2025/01/17\nWithdrawal: 2025/03/07"
  },
  {
    "Course Section": "CPSC_V 310-L2F - Introduction to Software Engineering",
    "Instructional Format": "Laboratory",
    "Section Status": "Closed",
    "Delivery Mode": "In Person Learning",
    "zCF - CT - Maximum Credits": "4 Credits",
    "zCF - CT - Enrolled/Capacity": "Enrolled/Capacity: 31/31",
    "Section Details": "Thu | 5:00 p.m. - 7:00 p.m. | 2025-01-09 - 2025-02-13",
    "Drop and Withdrawal Deadlines": "Drop: 2025/01/17\nWithdrawal: 2025/03/07"
  },
  {
    "Course Section": "CPSC_V 310-L2G - Introduction to Software Engineering",
    "Instructional Format": "Laboratory",
    "Section Status": "Open",
    "Delivery Mode": "In Person Learning",
    "zCF - CT - Maximum Credits": "4 Credits",
    "zCF - CT - Enrolled/Capacity": "Enrolled/Capacity: 30/31",
    "Section Details": "Mon | 9:00 a.m. - 11:00 a.m. | 2025-01-06 - 2025-02-10",
    "Drop and Withdrawal Deadlines": "Drop: 2025/01/17\nWithdrawal: 2025/03/07"
  },
  {
    "Course Section": "CPSC_V 310-L2H - Introduction to Software Engineering",
    "Instructional Format": "Laboratory",
    "Section Status": "Closed",
    "Delivery Mode": "In Person Learning",
    "zCF - CT - Maximum Credits": "4 Credits",
    "zCF - CT - Enrolled/Capacity": "Enrolled/Capacity: 31/31",
    "Section Details": "Mon | 11:00 a.m. - 1:00 p.m. | 2025-01-06 - 2025-02-10",
    "Drop and Withdrawal Deadlines": "Drop: 2025/01/17\nWithdrawal: 2025/03/07"
  },
  {
    "Course Section": "CPSC_V 310-L2J - Introduction to Software Engineering",
    "Instructional Format": "Laboratory",
    "Section Status": "Closed",
    "Delivery Mode": "In Person Learning",
    "zCF - CT - Maximum Credits": "4 Credits",
    "zCF - CT - Enrolled/Capacity": "Enrolled/Capacity: 31/31",
    "Section Details": "Mon | 1:00 p.m. - 3:00 p.m. | 2025-01-06 - 2025-02-10",
    "Drop and Withdrawal Deadlines": "Drop: 2025/01/17\nWithdrawal: 2025/03/07"
  },
  {
    "Course Section": "CPSC_V 310-L2K - Introduction to Software Engineering",
    "Instructional Format": "Laboratory",
    "Section Status": "Closed",
    "Delivery Mode": "In Person Learning",
    "zCF - CT - Maximum Credits": "4 Credits",
    "zCF - CT - Enrolled/Capacity": "Enrolled/Capacity: 31/31",
    "Section Details": "Wed | 12:00 p.m. - 2:00 p.m. | 2025-01-08 - 2025-02-12",
    "Drop and Withdrawal Deadlines": "Drop: 2025/01/17\nWithdrawal: 2025/03/07"
  },
  {
    "Course Section": "CPSC_V 310-L2M - Introduction to Software Engineering",
    "Instructional Format": "Laboratory",
    "Section Status": "Open",
    "Delivery Mode": "In Person Learning",
    "zCF - CT - Maximum Credits": "4 Credits",
    "zCF - CT - Enrolled/Capacity": "Enrolled/Capacity: 25/31",
    "Section Details": "Wed | 2:00 p.m. - 4:00 p.m. | 2025-01-08 - 2025-02-12",
    "Drop and Withdrawal Deadlines": "Drop: 2025/01/17\nWithdrawal: 2025/03/07"
  },
  {
    "Course Section": "CPSC_V 313-203 - Computer Hardware and Operating Systems",
    "Instructional Format": "Lecture",
    "Section Status": "Waitlist",
    "Delivery Mode": "In Person Learning",
    "zCF - CT - Maximum Credits": "3 Credits",
    "zCF - CT - Enrolled/Capacity": "Enrolled/Capacity: 195/195",
    "zCF - EE - Includes Reserved Seats": "Includes Reserved Seats",
    "zCF - EE - Waitlisted / Waitlist Capacity": "Waitlisted/Waitlist Capacity: 81/999",
    "Section Details": "CHBE-Floor 1-Room 101 | Mon Wed Fri | 11:00 a.m. - 12:00 p.m. | 2025-01-06 - 2025-02-14",
    "Instructors": "Patrice Belleville",
    "Drop and Withdrawal Deadlines": "Drop: 2025/01/17\nWithdrawal: 2025/03/07"
  },
  {
    "Course Section": "CPSC_V 313-204 - Computer Hardware and Operating Systems",
    "Instructional Format": "Lecture",
    "Section Status": "Waitlist",
    "Delivery Mode": "In Person Learning",
    "zCF - CT - Maximum Credits": "3 Credits",
    "zCF - CT - Enrolled/Capacity": "Enrolled/Capacity: 250/250",
    "zCF - EE - Includes Reserved Seats": "Includes Reserved Seats",
    "zCF - EE - Waitlisted / Waitlist Capacity": "Waitlisted/Waitlist Capacity: 30/999",
    "Section Details": "LIFE-Floor 2-Room 2201 | Mon Wed Fri | 2:00 p.m. - 3:00 p.m. | 2025-01-06 - 2025-02-14",
    "Instructors": "Patrice Belleville",
    "Drop and Withdrawal Deadlines": "Drop: 2025/01/17\nWithdrawal: 2025/03/07"
  },
  {
    "Course Section": "CPSC_V 313-T2A - Computer Hardware and Operating Systems",
    "Instructional Format": "Discussion",
    "Section Status": "Closed",
    "Delivery Mode": "In Person Learning",
    "zCF - CT - Maximum Credits": "3 Credits",
    "zCF - CT - Enrolled/Capacity": "Enrolled/Capacity: 42/42",
    "Section Details": "CEME-Floor 1-Room 1215 | Thu | 12:30 p.m. - 1:30 p.m. | 2025-01-09 - 2025-02-13",
    "Drop and Withdrawal Deadlines": "Drop: 2025/01/17\nWithdrawal: 2025/03/07"
  },
  {
    "Course Section": "CPSC_V 313-T2B - Computer Hardware and Operating Systems",
    "Instructional Format": "Discussion",
    "Section Status": "Open",
    "Delivery Mode": "In Person Learning",
    "zCF - CT - Maximum Credits": "3 Credits",
    "zCF - CT - Enrolled/Capacity": "Enrolled/Capacity: 41/42",
    "Section Details": "DMP-Floor 2-Room 201 | Wed | 3:00 p.m. - 4:00 p.m. | 2025-01-08 - 2025-02-12",
    "Drop and Withdrawal Deadlines": "Drop: 2025/01/17\nWithdrawal: 2025/03/07"
  },
  {
    "Course Section": "CPSC_V 313-T2C - Computer Hardware and Operating Systems",
    "Instructional Format": "Discussion",
    "Section Status": "Open",
    "Delivery Mode": "In Person Learning",
    "zCF - CT - Maximum Credits": "3 Credits",
    "zCF - CT - Enrolled/Capacity": "Enrolled/Capacity: 41/42",
    "Section Details": "DMP-Floor 1-Room 101 | Fri | 3:00 p.m. - 4:00 p.m. | 2025-01-10 - 2025-02-14",
    "Drop and Withdrawal Deadlines": "Drop: 2025/01/17\nWithdrawal: 2025/03/07"
  },
  {
    "Course Section": "CPSC_V 313-T2D - Computer Hardware and Operating Systems",
    "Instructional Format": "Discussion",
    "Section Status": "Closed",
    "Delivery Mode": "In Person Learning",
    "zCF - CT - Maximum Credits": "3 Credits",
    "zCF - CT - Enrolled/Capacity": "Enrolled/Capacity: 42/42",
    "Section Details": "FSC-Floor 1-Room 1611 | Thu | 10:00 a.m. - 11:00 a.m. | 2025-01-09 - 2025-02-13",
    "Drop and Withdrawal Deadlines": "Drop: 2025/01/17\nWithdrawal: 2025/03/07"
  },
  {
    "Course Section": "CPSC_V 313-T2E - Computer Hardware and Operating Systems",
    "Instructional Format": "Discussion",
    "Section Status": "Closed",
    "Delivery Mode": "In Person Learning",
    "zCF - CT - Maximum Credits": "3 Credits",
    "zCF - CT - Enrolled/Capacity": "Enrolled/Capacity: 42/42",
    "Section Details": "DMP-Floor 2-Room 201 | Wed | 5:00 p.m. - 6:00 p.m. | 2025-01-08 - 2025-02-12",
    "Drop and Withdrawal Deadlines": "Drop: 2025/01/17\nWithdrawal: 2025/03/07"
  },
  {
    "Course Section": "CPSC_V 313-T2F - Computer Hardware and Operating Systems",
    "Instructional Format": "Discussion",
    "Section Status": "Closed",
    "Delivery Mode": "In Person Learning",
    "zCF - CT - Maximum Credits": "3 Credits",
    "zCF - CT - Enrolled/Capacity": "Enrolled/Capacity: 42/42",
    "Section Details": "MCLD-Floor 3-Room 3018 | Fri | 10:00 a.m. - 11:00 a.m. | 2025-01-10 - 2025-02-14",
    "Drop and Withdrawal Deadlines": "Drop: 2025/01/17\nWithdrawal: 2025/03/07"
  },
  {
    "Course Section": "CPSC_V 313-T2G - Computer Hardware and Operating Systems",
    "Instructional Format": "Discussion",
    "Section Status": "Closed",
    "Delivery Mode": "In Person Learning",
    "zCF - CT - Maximum Credits": "3 Credits",
    "zCF - CT - Enrolled/Capacity": "Enrolled/Capacity: 42/42",
    "Section Details": "DMP-Floor 1-Room 101 | Thu | 5:00 p.m. - 6:00 p.m. | 2025-01-09 - 2025-02-13",
    "Drop and Withdrawal Deadlines": "Drop: 2025/01/17\nWithdrawal: 2025/03/07"
  },
  {
    "Course Section": "CPSC_V 313-T2H - Computer Hardware and Operating Systems",
    "Instructional Format": "Discussion",
    "Section Status": "Closed",
    "Delivery Mode": "In Person Learning",
    "zCF - CT - Maximum Credits": "3 Credits",
    "zCF - CT - Enrolled/Capacity": "Enrolled/Capacity: 42/42",
    "Section Details": "CHBE-Floor 1-Room 103 | Wed | 1:00 p.m. - 2:00 p.m. | 2025-01-08 - 2025-02-12",
    "Drop and Withdrawal Deadlines": "Drop: 2025/01/17\nWithdrawal: 2025/03/07"
  },
  {
    "Course Section": "CPSC_V 313-T2K - Computer Hardware and Operating Systems",
    "Instructional Format": "Discussion",
    "Section Status": "Closed",
    "Delivery Mode": "In Person Learning",
    "zCF - CT - Maximum Credits": "3 Credits",
    "zCF - CT - Enrolled/Capacity": "Enrolled/Capacity: 42/42",
    "Section Details": "DMP-Floor 1-Room 101 | Fri | 4:00 p.m. - 5:00 p.m. | 2025-01-10 - 2025-02-14",
    "Drop and Withdrawal Deadlines": "Drop: 2025/01/17\nWithdrawal: 2025/03/07"
  },
  {
    "Course Section": "CPSC_V 313-T2L - Computer Hardware and Operating Systems",
    "Instructional Format": "Discussion",
    "Section Status": "Closed",
    "Delivery Mode": "In Person Learning",
    "zCF - CT - Maximum Credits": "3 Credits",
    "zCF - CT - Enrolled/Capacity": "Enrolled/Capacity: 42/42",
    "Section Details": "CEME-Floor 1-Room 1215 | Tue | 10:00 a.m. - 11:00 a.m. | 2025-01-07 - 2025-02-11",
    "Drop and Withdrawal Deadlines": "Drop: 2025/01/17\nWithdrawal: 2025/03/07"
  },
  {
    "Course Section": "CPSC_V 313-T2M - Computer Hardware and Operating Systems",
    "Instructional Format": "Discussion",
    "Section Status": "Open",
    "Delivery Mode": "In Person Learning",
    "zCF - CT - Maximum Credits": "3 Credits",
    "zCF - CT - Enrolled/Capacity": "Enrolled/Capacity: 25/42",
    "Section Details": "SWNG-Floor 1-Room 105 | Fri | 1:00 p.m. - 2:00 p.m. | 2025-01-10 - 2025-02-14",
    "Drop and Withdrawal Deadlines": "Drop: 2025/01/17\nWithdrawal: 2025/03/07"
  },
  {
    "Course Section": "CPSC_V 314-201 - Computer Graphics",
    "Instructional Format": "Lecture",
    "Section Status": "Waitlist",
    "Delivery Mode": "In Person Learning",
    "zCF - CT - Maximum Credits": "3 Credits",
    "zCF - CT - Enrolled/Capacity": "Enrolled/Capacity: 164/164",
    "zCF - EE - Includes Reserved Seats": "Includes Reserved Seats",
    "zCF - EE - Waitlisted / Waitlist Capacity": "Waitlisted/Waitlist Capacity: 42/999",
    "Section Details": "LSK-Floor 2-Room 200 | Mon Wed Fri | 10:00 a.m. - 11:00 a.m. | 2025-01-06 - 2025-02-14",
    "Instructors": "Dinesh Pai",
    "Drop and Withdrawal Deadlines": "Drop: 2025/01/17\nWithdrawal: 2025/03/07"
  },
  {
    "Course Section": "CPSC_V 314-L2A - Computer Graphics",
    "Instructional Format": "Laboratory",
    "Section Status": "Closed",
    "Delivery Mode": "In Person Learning",
    "zCF - CT - Maximum Credits": "3 Credits",
    "zCF - CT - Enrolled/Capacity": "Enrolled/Capacity: 25/25",
    "Section Details": "ICCS-Floor B1-Room 005 | Thu | 2:30 p.m. - 3:30 p.m. | 2025-01-09 - 2025-02-13",
    "Drop and Withdrawal Deadlines": "Drop: 2025/01/17\nWithdrawal: 2025/03/07"
  },
  {
    "Course Section": "CPSC_V 314-L2B - Computer Graphics",
    "Instructional Format": "Laboratory",
    "Section Status": "Open",
    "Delivery Mode": "In Person Learning",
    "zCF - CT - Maximum Credits": "3 Credits",
    "zCF - CT - Enrolled/Capacity": "Enrolled/Capacity: 19/25",
    "Section Details": "ICCS-Floor B1-Room 005 | Wed | 3:00 p.m. - 4:00 p.m. | 2025-01-08 - 2025-02-12",
    "Drop and Withdrawal Deadlines": "Drop: 2025/01/17\nWithdrawal: 2025/03/07"
  },
  {
    "Course Section": "CPSC_V 314-L2C - Computer Graphics",
    "Instructional Format": "Laboratory",
    "Section Status": "Open",
    "Delivery Mode": "In Person Learning",
    "zCF - CT - Maximum Credits": "3 Credits",
    "zCF - CT - Enrolled/Capacity": "Enrolled/Capacity: 24/25",
    "Section Details": "ICCS-Floor B1-Room 005 | Wed | 12:00 p.m. - 1:00 p.m. | 2025-01-08 - 2025-02-12",
    "Drop and Withdrawal Deadlines": "Drop: 2025/01/17\nWithdrawal: 2025/03/07"
  },
  {
    "Course Section": "CPSC_V 314-L2D - Computer Graphics",
    "Instructional Format": "Laboratory",
    "Section Status": "Open",
    "Delivery Mode": "In Person Learning",
    "zCF - CT - Maximum Credits": "3 Credits",
    "zCF - CT - Enrolled/Capacity": "Enrolled/Capacity: 22/25",
    "Section Details": "ICCS-Floor B1-Room 005 | Thu | 3:30 p.m. - 4:30 p.m. | 2025-01-09 - 2025-02-13",
    "Drop and Withdrawal Deadlines": "Drop: 2025/01/17\nWithdrawal: 2025/03/07"
  },
  {
    "Course Section": "CPSC_V 314-L2E - Computer Graphics",
    "Instructional Format": "Laboratory",
    "Section Status": "Closed",
    "Delivery Mode": "In Person Learning",
    "zCF - CT - Maximum Credits": "3 Credits",
    "zCF - CT - Enrolled/Capacity": "Enrolled/Capacity: 25/25",
    "Section Details": "ICCS-Floor B1-Room 005 | Wed | 1:00 p.m. - 2:00 p.m. | 2025-01-08 - 2025-02-12",
    "Drop and Withdrawal Deadlines": "Drop: 2025/01/17\nWithdrawal: 2025/03/07"
  },
  {
    "Course Section": "CPSC_V 314-L2F - Computer Graphics",
    "Instructional Format": "Laboratory",
    "Section Status": "Open",
    "Delivery Mode": "In Person Learning",
    "zCF - CT - Maximum Credits": "3 Credits",
    "zCF - CT - Enrolled/Capacity": "Enrolled/Capacity: 24/25",
    "Section Details": "ICCS-Floor B1-Room 005 | Thu | 11:00 a.m. - 12:00 p.m. | 2025-01-09 - 2025-02-13",
    "Drop and Withdrawal Deadlines": "Drop: 2025/01/17\nWithdrawal: 2025/03/07"
  },
  {
    "Course Section": "CPSC_V 314-L2G - Computer Graphics",
    "Instructional Format": "Laboratory",
    "Section Status": "Closed",
    "Delivery Mode": "In Person Learning",
    "zCF - CT - Maximum Credits": "3 Credits",
    "zCF - CT - Enrolled/Capacity": "Enrolled/Capacity: 25/25",
    "Section Details": "ICCS-Floor B1-Room 005 | Tue | 11:00 a.m. - 12:00 p.m. | 2025-01-07 - 2025-02-11",
    "Drop and Withdrawal Deadlines": "Drop: 2025/01/17\nWithdrawal: 2025/03/07"
  },
  {
    "Course Section": "CPSC_V 317-201 - Introduction to Computer Networking",
    "Instructional Format": "Lecture",
    "Section Status": "Open",
    "Delivery Mode": "In Person Learning",
    "zCF - CT - Maximum Credits": "3 Credits",
    "zCF - CT - Enrolled/Capacity": "Enrolled/Capacity: 147/154",
    "zCF - EE - Includes Reserved Seats": "Includes Reserved Seats",
    "zCF - EE - Waitlisted / Waitlist Capacity": "Waitlisted/Waitlist Capacity: 72/999",
    "Section Details": "ESB-Floor 1-Room 1012 | Mon Wed Fri | 3:00 p.m. - 4:00 p.m. | 2025-01-06 - 2025-02-14",
    "Drop and Withdrawal Deadlines": "Drop: 2025/01/17\nWithdrawal: 2025/03/07"
  },
  {
    "Course Section": "CPSC_V 317-202 - Introduction to Computer Networking",
    "Instructional Format": "Lecture",
    "Section Status": "Open",
    "Delivery Mode": "In Person Learning",
    "zCF - CT - Maximum Credits": "3 Credits",
    "zCF - CT - Enrolled/Capacity": "Enrolled/Capacity: 146/154",
    "zCF - EE - Includes Reserved Seats": "Includes Reserved Seats",
    "zCF - EE - Waitlisted / Waitlist Capacity": "Waitlisted/Waitlist Capacity: 139/999",
    "Section Details": "MCML-Floor 3-Room 360 | Mon Wed Fri | 11:00 a.m. - 12:00 p.m. | 2025-01-06 - 2025-02-14",
    "Drop and Withdrawal Deadlines": "Drop: 2025/01/17\nWithdrawal: 2025/03/07"
  },
  {
    "Course Section": "CPSC_V 317-T2A - Introduction to Computer Networking",
    "Instructional Format": "Discussion",
    "Section Status": "Open",
    "Delivery Mode": "In Person Learning",
    "zCF - CT - Maximum Credits": "3 Credits",
    "zCF - CT - Enrolled/Capacity": "Enrolled/Capacity: 38/41",
    "Section Details": "FSC-Floor 1-Room 1611 | Thu | 4:00 p.m. - 5:00 p.m. | 2025-01-09 - 2025-02-13",
    "Drop and Withdrawal Deadlines": "Drop: 2025/01/17\nWithdrawal: 2025/03/07"
  },
  {
    "Course Section": "CPSC_V 317-T2B - Introduction to Computer Networking",
    "Instructional Format": "Discussion",
    "Section Status": "Open",
    "Delivery Mode": "In Person Learning",
    "zCF - CT - Maximum Credits": "3 Credits",
    "zCF - CT - Enrolled/Capacity": "Enrolled/Capacity: 40/41",
    "Section Details": "CEME-Floor 1-Room 1215 | Fri | 9:00 a.m. - 10:00 a.m. | 2025-01-10 - 2025-02-14",
    "Drop and Withdrawal Deadlines": "Drop: 2025/01/17\nWithdrawal: 2025/03/07"
  },
  {
    "Course Section": "CPSC_V 317-T2C - Introduction to Computer Networking",
    "Instructional Format": "Discussion",
    "Section Status": "Closed",
    "Delivery Mode": "In Person Learning",
    "zCF - CT - Maximum Credits": "3 Credits",
    "zCF - CT - Enrolled/Capacity": "Enrolled/Capacity: 41/41",
    "Section Details": "DMP-Floor 1-Room 101 | Fri | 12:00 p.m. - 1:00 p.m. | 2025-01-10 - 2025-02-14",
    "Drop and Withdrawal Deadlines": "Drop: 2025/01/17\nWithdrawal: 2025/03/07"
  },
  {
    "Course Section": "CPSC_V 317-T2D - Introduction to Computer Networking",
    "Instructional Format": "Discussion",
    "Section Status": "Open",
    "Delivery Mode": "In Person Learning",
    "zCF - CT - Maximum Credits": "3 Credits",
    "zCF - CT - Enrolled/Capacity": "Enrolled/Capacity: 40/41",
    "Section Details": "DMP-Floor 2-Room 201 | Thu | 2:00 p.m. - 3:00 p.m. | 2025-01-09 - 2025-02-13",
    "Drop and Withdrawal Deadlines": "Drop: 2025/01/17\nWithdrawal: 2025/03/07"
  },
  {
    "Course Section": "CPSC_V 317-T2E - Introduction to Computer Networking",
    "Instructional Format": "Discussion",
    "Section Status": "Open",
    "Delivery Mode": "In Person Learning",
    "zCF - CT - Maximum Credits": "3 Credits",
    "zCF - CT - Enrolled/Capacity": "Enrolled/Capacity: 32/41",
    "Section Details": "DMP-Floor 2-Room 201 | Thu | 5:00 p.m. - 6:00 p.m. | 2025-01-09 - 2025-02-13",
    "Drop and Withdrawal Deadlines": "Drop: 2025/01/17\nWithdrawal: 2025/03/07"
  },
  {
    "Course Section": "CPSC_V 317-T2F - Introduction to Computer Networking",
    "Instructional Format": "Discussion",
    "Section Status": "Open",
    "Delivery Mode": "In Person Learning",
    "zCF - CT - Maximum Credits": "3 Credits",
    "zCF - CT - Enrolled/Capacity": "Enrolled/Capacity: 38/41",
    "Section Details": "MCML-Floor 1-Room 158 | Fri | 10:00 a.m. - 11:00 a.m. | 2025-01-10 - 2025-02-14",
    "Drop and Withdrawal Deadlines": "Drop: 2025/01/17\nWithdrawal: 2025/03/07"
  },
  {
    "Course Section": "CPSC_V 317-T2G - Introduction to Computer Networking",
    "Instructional Format": "Discussion",
    "Section Status": "Closed",
    "Delivery Mode": "In Person Learning",
    "zCF - CT - Maximum Credits": "3 Credits",
    "zCF - CT - Enrolled/Capacity": "Enrolled/Capacity: 41/41",
    "Section Details": "MCLD-Floor 3-Room 3008 | Wed | 1:00 p.m. - 2:00 p.m. | 2025-01-08 - 2025-02-12",
    "Drop and Withdrawal Deadlines": "Drop: 2025/01/17\nWithdrawal: 2025/03/07"
  },
  {
    "Course Section": "CPSC_V 317-T2H - Introduction to Computer Networking",
    "Instructional Format": "Discussion",
    "Section Status": "Open",
    "Delivery Mode": "In Person Learning",
    "zCF - CT - Maximum Credits": "3 Credits",
    "zCF - CT - Enrolled/Capacity": "Enrolled/Capacity: 22/41",
    "Section Details": "DMP-Floor 2-Room 201 | Wed | 6:00 p.m. - 7:00 p.m. | 2025-01-08 - 2025-02-12",
    "Drop and Withdrawal Deadlines": "Drop: 2025/01/17\nWithdrawal: 2025/03/07"
  },
  {
    "Course Section": "CPSC_V 319-201 - Software Engineering Project",
    "Instructional Format": "Lecture",
    "Section Status": "Open",
    "Delivery Mode": "In Person Learning",
    "zCF - CT - Maximum Credits": "4 Credits",
    "zCF - CT - Enrolled/Capacity": "Enrolled/Capacity: 86/93",
    "zCF - EE - Includes Reserved Seats": "Includes Reserved Seats",
    "zCF - EE - Waitlisted / Waitlist Capacity": "Waitlisted/Waitlist Capacity: 53/999",
    "Section Details": "MCLD-Floor 2-Room 2018 | Mon Wed | 5:30 p.m. - 7:00 p.m. | 2025-01-06 - 2025-02-12",
    "Course Section Definition Public Notes": "This course is a team based project course that utilizes real world industry sponsors from a variety of industries including Financial Services, Technology, Engineering, Consulting or Health Services organizations.\n\nPlease see previous course outline for details at:\nhttps://www.students.cs.ubc.ca/~cs-319/",
    "Instructors": "Jerry Jim",
    "Drop and Withdrawal Deadlines": "Drop: 2025/01/17\nWithdrawal: 2025/03/07"
  },
  {
    "Course Section": "CPSC_V 320-201 - Intermediate Algorithm Design and Analysis",
    "Instructional Format": "Lecture",
    "Section Status": "Open",
    "Delivery Mode": "In Person Learning",
    "zCF - CT - Maximum Credits": "3 Credits",
    "zCF - CT - Enrolled/Capacity": "Enrolled/Capacity: 170/185",
    "zCF - EE - Includes Reserved Seats": "Includes Reserved Seats",
    "zCF - EE - Waitlisted / Waitlist Capacity": "Waitlisted/Waitlist Capacity: 74/999",
    "Section Details": "SWNG-Floor 2-Room 221 | Mon Wed Fri | 10:00 a.m. - 11:00 a.m. | 2025-01-06 - 2025-02-14",
    "Course Section Definition Public Notes": "If Workday indicates that you do not meet the CPSC 320 prerequisites, but you have taken CPSC 221 and one of the courses credit-excluded with STAT 200 in the UBC Science Credit Exclusion List, then you may submit a Request for Registration Assistance Form as described at:\nhttps://www.cs.ubc.ca/students/undergrad/courses-deadlines/cpsc-appeals-steps-undergraduate-students.\n\nPlease ensure that you include in your message exactly what course that you have taken is credit-excluded with STAT 200 and which section(s) of CPSC 320 (lecture and tutorial) you are interested in, in priority order. Requests that do not follow these guidelines may be denied without consideration.\n\nIf your request is approved, we will either grant you permission to register yourself (if your registration date has not yet arrived), register you for a lecture and tutorial section (if it has and a seat is available), or otherwise: waitlist you with an effective waitlist date no later than the next business day after the date your request for registration assistance included complete information.",
    "Instructors": "Susanne Bradley",
    "Drop and Withdrawal Deadlines": "Drop: 2025/01/17\nWithdrawal: 2025/03/07"
  },
  {
    "Course Section": "CPSC_V 320-202 - Intermediate Algorithm Design and Analysis",
    "Instructional Format": "Lecture",
    "Section Status": "Open",
    "Delivery Mode": "In Person Learning",
    "zCF - CT - Maximum Credits": "3 Credits",
    "zCF - CT - Enrolled/Capacity": "Enrolled/Capacity: 184/226",
    "zCF - EE - Includes Reserved Seats": "Includes Reserved Seats",
    "zCF - EE - Waitlisted / Waitlist Capacity": "Waitlisted/Waitlist Capacity: 32/999",
    "Section Details": "HEBB-Floor 1-Room 100 | Mon Wed Fri | 4:00 p.m. - 5:00 p.m. | 2025-01-06 - 2025-02-14",
    "Course Section Definition Public Notes": "If Workday indicates that you do not meet the CPSC 320 prerequisites, but you have taken CPSC 221 and one of the courses credit-excluded with STAT 200 in the UBC Science Credit Exclusion List, then you may submit a Request for Registration Assistance Form as described at:\nhttps://www.cs.ubc.ca/students/undergrad/courses-deadlines/cpsc-appeals-steps-undergraduate-students.\n\nPlease ensure that you include in your message exactly what course that you have taken is credit-excluded with STAT 200 and which section(s) of CPSC 320 (lecture and tutorial) you are interested in, in priority order. Requests that do not follow these guidelines may be denied without consideration.\n\nIf your request is approved, we will either grant you permission to register yourself (if your registration date has not yet arrived), register you for a lecture and tutorial section (if it has and a seat is available), or otherwise: waitlist you with an effective waitlist date no later than the next business day after the date your request for registration assistance included complete information.",
    "Instructors": "Alan Hu",
    "Drop and Withdrawal Deadlines": "Drop: 2025/01/17\nWithdrawal: 2025/03/07"
  },
  {
    "Course Section": "CPSC_V 320-203 - Intermediate Algorithm Design and Analysis",
    "Instructional Format": "Lecture",
    "Section Status": "Open",
    "Delivery Mode": "In Person Learning",
    "zCF - CT - Maximum Credits": "3 Credits",
    "zCF - CT - Enrolled/Capacity": "Enrolled/Capacity: 222/226",
    "zCF - EE - Includes Reserved Seats": "Includes Reserved Seats",
    "zCF - EE - Waitlisted / Waitlist Capacity": "Waitlisted/Waitlist Capacity: 80/999",
    "Section Details": "BIOL-Floor 1-Room 1000 | Mon Wed Fri | 1:00 p.m. - 2:00 p.m. | 2025-01-06 - 2025-02-14",
    "Course Section Definition Public Notes": "If Workday indicates that you do not meet the CPSC 320 prerequisites, but you have taken CPSC 221 and one of the courses credit-excluded with STAT 200 in the UBC Science Credit Exclusion List, then you may submit a Request for Registration Assistance Form as described at:\nhttps://www.cs.ubc.ca/students/undergrad/courses-deadlines/cpsc-appeals-steps-undergraduate-students.\n\nPlease ensure that you include in your message exactly what course that you have taken is credit-excluded with STAT 200 and which section(s) of CPSC 320 (lecture and tutorial) you are interested in, in priority order. Requests that do not follow these guidelines may be denied without consideration.\n\nIf your request is approved, we will either grant you permission to register yourself (if your registration date has not yet arrived), register you for a lecture and tutorial section (if it has and a seat is available), or otherwise: waitlist you with an effective waitlist date no later than the next business day after the date your request for registration assistance included complete information.",
    "Instructors": "Susanne Bradley",
    "Drop and Withdrawal Deadlines": "Drop: 2025/01/17\nWithdrawal: 2025/03/07"
  },
  {
    "Course Section": "CPSC_V 320-T2A - Intermediate Algorithm Design and Analysis",
    "Instructional Format": "Discussion",
    "Section Status": "Open",
    "Delivery Mode": "In Person Learning",
    "zCF - CT - Maximum Credits": "3 Credits",
    "zCF - CT - Enrolled/Capacity": "Enrolled/Capacity: 83/84",
    "Section Details": "MCLD-Floor 2-Room 2002 | Mon | 5:00 p.m. - 6:00 p.m. | 2025-01-06 - 2025-02-10",
    "Drop and Withdrawal Deadlines": "Drop: 2025/01/17\nWithdrawal: 2025/03/07"
  },
  {
    "Course Section": "CPSC_V 320-T2B - Intermediate Algorithm Design and Analysis",
    "Instructional Format": "Discussion",
    "Section Status": "Open",
    "Delivery Mode": "In Person Learning",
    "zCF - CT - Maximum Credits": "3 Credits",
    "zCF - CT - Enrolled/Capacity": "Enrolled/Capacity: 83/84",
    "Section Details": "MCLD-Floor 2-Room 2002 | Wed | 12:00 p.m. - 1:00 p.m. | 2025-01-08 - 2025-02-12",
    "Drop and Withdrawal Deadlines": "Drop: 2025/01/17\nWithdrawal: 2025/03/07"
  },
  {
    "Course Section": "CPSC_V 320-T2C - Intermediate Algorithm Design and Analysis",
    "Instructional Format": "Discussion",
    "Section Status": "Open",
    "Delivery Mode": "In Person Learning",
    "zCF - CT - Maximum Credits": "3 Credits",
    "zCF - CT - Enrolled/Capacity": "Enrolled/Capacity: 31/84",
    "Section Details": "DMP-Floor 3-Room 301 | Tue | 9:00 a.m. - 10:00 a.m. | 2025-01-07 - 2025-02-11",
    "Drop and Withdrawal Deadlines": "Drop: 2025/01/17\nWithdrawal: 2025/03/07"
  },
  {
    "Course Section": "CPSC_V 320-T2D - Intermediate Algorithm Design and Analysis",
    "Instructional Format": "Discussion",
    "Section Status": "Closed",
    "Delivery Mode": "In Person Learning",
    "zCF - CT - Maximum Credits": "3 Credits",
    "zCF - CT - Enrolled/Capacity": "Enrolled/Capacity: 84/84",
    "Section Details": "DMP-Floor 3-Room 301 | Tue | 1:00 p.m. - 2:00 p.m. | 2025-01-07 - 2025-02-11",
    "Drop and Withdrawal Deadlines": "Drop: 2025/01/17\nWithdrawal: 2025/03/07"
  },
  {
    "Course Section": "CPSC_V 320-T2E - Intermediate Algorithm Design and Analysis",
    "Instructional Format": "Discussion",
    "Section Status": "Closed",
    "Delivery Mode": "In Person Learning",
    "zCF - CT - Maximum Credits": "3 Credits",
    "zCF - CT - Enrolled/Capacity": "Enrolled/Capacity: 84/84",
    "Section Details": "DMP-Floor 3-Room 301 | Tue | 11:00 a.m. - 12:00 p.m. | 2025-01-07 - 2025-02-11",
    "Drop and Withdrawal Deadlines": "Drop: 2025/01/17\nWithdrawal: 2025/03/07"
  },
  {
    "Course Section": "CPSC_V 320-T2F - Intermediate Algorithm Design and Analysis",
    "Instructional Format": "Discussion",
    "Section Status": "Open",
    "Delivery Mode": "In Person Learning",
    "zCF - CT - Maximum Credits": "3 Credits",
    "zCF - CT - Enrolled/Capacity": "Enrolled/Capacity: 68/84",
    "Section Details": "DMP-Floor 3-Room 301 | Thu | 10:00 a.m. - 11:00 a.m. | 2025-01-09 - 2025-02-13",
    "Drop and Withdrawal Deadlines": "Drop: 2025/01/17\nWithdrawal: 2025/03/07"
  }
]