[
  {
    "Course Section": "COMM_V 294-202 - Managerial Accounting",
    "Instructional Format": "Lecture",
    "Section Status": "Waitlist",
    "Delivery Mode": "In Person Learning",
    "Course Section Definition Public Notes": "This section is restricted to students in Year 2 or higher of the Bachelor of Commerce program.",
    "Drop and Withdrawal Deadlines": "Drop: 2025/01/17&#xa;Withdrawal: 2025/03/07"
  },
  {
    "Course Section": "COMM_V 294-203 - Managerial Accounting",
    "Instructional Format": "Lecture",
    "Section Status": "Waitlist",
    "Delivery Mode": "In Person Learning",
    "Course Section Definition Public Notes": "This section is restricted to students in Year 2 or higher of the Bachelor of Commerce program.",
    "Drop and Withdrawal Deadlines": "Drop: 2025/01/17&#xa;Withdrawal: 2025/03/07"
  },
  {
    "Course Section": "COMM_V 296-201 - Introduction to Marketing",
    "Instructional Format": "Lecture",
    "Section Status": "Open",
    "Delivery Mode": "In Person Learning",
    "Course Section Definition Public Notes": "This section is restricted to students in Year 2 or higher of the Bachelor of Commerce program.",
    "Drop and Withdrawal Deadlines": "Drop: 2025/01/17&#xa;Withdrawal: 2025/03/07"
  },
  {
    "Course Section": "COMM_V 296-202 - Introduction to Marketing",
    "Instructional Format": "Lecture",
    "Section Status": "Waitlist",
    "Delivery Mode": "In Person Learning",
    "Course Section Definition Public Notes": "This section is restricted to students in Year 2 or higher of the Bachelor of Commerce program.",
    "Drop and Withdrawal Deadlines": "Drop: 2025/01/17&#xa;Withdrawal: 2025/03/07"
  },
  {
    "Course Section": "COMM_V 296-203 - Introduction to Marketing",
    "Instructional Format": "Lecture",
    "Section Status": "Closed",
    "Delivery Mode": "In Person Learning",
    "Course Section Definition Public Notes": "This section is restricted to students in Year 2 or higher of the Bachelor of Commerce program.",
    "Drop and Withdrawal Deadlines": "Drop: 2025/01/17&#xa;Withdrawal: 2025/03/07"
  },
  {
    "Course Section": "COMM_V 296-204 - Introduction to Marketing",
    "Instructional Format": "Lecture",
    "Section Status": "Closed",
    "Delivery Mode": "In Person Learning",
    "Course Section Definition Public Notes": "This section is restricted to students in Year 2 or higher of the Bachelor of Commerce program.",
    "Drop and Withdrawal Deadlines": "Drop: 2025/01/17&#xa;Withdrawal: 2025/03/07"
  },
  {
    "Course Section": "COMM_V 296-205 - Introduction to Marketing",
    "Instructional Format": "Lecture",
    "Section Status": "Closed",
    "Delivery Mode": "In Person Learning",
    "Course Section Definition Public Notes": "This section is restricted to students in Year 2 or higher of the Bachelor of Commerce program.",
    "Drop and Withdrawal Deadlines": "Drop: 2025/01/17&#xa;Withdrawal: 2025/03/07"
  },
  {
    "Course Section": "COMM_V 296-206 - Introduction to Marketing",
    "Instructional Format": "Lecture",
    "Section Status": "Closed",
    "Delivery Mode": "In Person Learning",
    "Course Section Definition Public Notes": "This section is restricted to students in Year 2 or higher of the Bachelor of Commerce program.",
    "Drop and Withdrawal Deadlines": "Drop: 2025/01/17&#xa;Withdrawal: 2025/03/07"
  },
  {
    "Course Section": "COMM_V 296-207 - Introduction to Marketing",
    "Instructional Format": "Lecture",
    "Section Status": "Closed",
    "Delivery Mode": "In Person Learning",
    "Course Section Definition Public Notes": "This section is restricted to students in Year 2 or higher of the Bachelor of Commerce program.",
    "Drop and Withdrawal Deadlines": "Drop: 2025/01/17&#xa;Withdrawal: 2025/03/07"
  },
  {
    "Course Section": "COMM_V 298-201 - Introduction to Finance",
    "Instructional Format": "Lecture",
    "Section Status": "Open",
    "Delivery Mode": "In Person Learning",
    "Course Section Definition Public Notes": "This section is restricted to students in Year 2 or higher of the Bachelor of Commerce program.",
    "Drop and Withdrawal Deadlines": "Drop: 2025/01/17&#xa;Withdrawal: 2025/03/07"
  },
  {
    "Course Section": "COMM_V 298-202 - Introduction to Finance",
    "Instructional Format": "Lecture",
    "Section Status": "Waitlist",
    "Delivery Mode": "In Person Learning",
    "Course Section Definition Public Notes": "This section is restricted to students in Year 2 or higher of the Bachelor of Commerce program.",
    "Drop and Withdrawal Deadlines": "Drop: 2025/01/17&#xa;Withdrawal: 2025/03/07"
  },
  {
    "Course Section": "COMM_V 298-203 - Introduction to Finance",
    "Instructional Format": "Lecture",
    "Section Status": "Waitlist",
    "Delivery Mode": "In Person Learning",
    "Course Section Definition Public Notes": "This section is restricted to students in Year 2 or higher of the Bachelor of Commerce program.",
    "Drop and Withdrawal Deadlines": "Drop: 2025/01/17&#xa;Withdrawal: 2025/03/07"
  },
  {
    "Course Section": "COMM_V 298-204 - Introduction to Finance",
    "Instructional Format": "Lecture",
    "Section Status": "Waitlist",
    "Delivery Mode": "In Person Learning",
    "Course Section Definition Public Notes": "This section is restricted to students in Year 2 or higher of the Bachelor of Commerce program.",
    "Drop and Withdrawal Deadlines": "Drop: 2025/01/17&#xa;Withdrawal: 2025/03/07"
  },
  {
    "Course Section": "COMM_V 298-205 - Introduction to Finance",
    "Instructional Format": "Lecture",
    "Section Status": "Open",
    "Delivery Mode": "In Person Learning",
    "Course Section Definition Public Notes": "This section is restricted to students in Year 2 or higher of the Bachelor of Commerce program.",
    "Drop and Withdrawal Deadlines": "Drop: 2025/01/17&#xa;Withdrawal: 2025/03/07"
  },
  {
    "Course Section": "COMM_V 298-206 - Introduction to Finance",
    "Instructional Format": "Lecture",
    "Section Status": "Closed",
    "Delivery Mode": "In Person Learning",
    "Course Section Definition Public Notes": "This section is restricted to students in Year 2 or higher of the Bachelor of Commerce program.",
    "Drop and Withdrawal Deadlines": "Drop: 2025/01/17&#xa;Withdrawal: 2025/03/07"
  },
  {
    "Course Section": "COMM_V 298-207 - Introduction to Finance",
    "Instructional Format": "Lecture",
    "Section Status": "Waitlist",
    "Delivery Mode": "In Person Learning",
    "Course Section Definition Public Notes": "This section is restricted to students in Year 2 or higher of the Bachelor of Commerce program.",
    "Drop and Withdrawal Deadlines": "Drop: 2025/01/17&#xa;Withdrawal: 2025/03/07"
  },
  {
    "Course Section": "COMR_V 280-201 - Entrepreneurship",
    "Instructional Format": "Lecture",
    "Section Status": "Open",
    "Delivery Mode": "In Person Learning",
    "Course Section Definition Public Notes": "This section is restricted to students with Minor in Entrepreneurship.",
    "Drop and Withdrawal Deadlines": "Drop: 2025/01/17&#xa;Withdrawal: 2025/03/07"
  },
  {
    "Course Section": "COMR_V 280-202 - Entrepreneurship",
    "Instructional Format": "Lecture",
    "Section Status": "Open",
    "Delivery Mode": "In Person Learning",
    "Course Section Definition Public Notes": "This section is restricted to students with Minor in Entrepreneurship.",
    "Drop and Withdrawal Deadlines": "Drop: 2025/01/17&#xa;Withdrawal: 2025/03/07"
  },
  {
    "Course Section": "CONS_V 200-002 - Foundations of Conservation",
    "Instructional Format": "Lecture",
    "Section Status": "Open",
    "Delivery Mode": "In Person Learning",
    "Drop and Withdrawal Deadlines": "Drop: 2025/01/17&#xa;Withdrawal: 2025/03/07"
  },
  {
    "Course Section": "CPEN_V 212-201 - Computing Systems II",
    "Instructional Format": "Lecture",
    "Section Status": "Waitlist",
    "Delivery Mode": "In Person Learning",
    "Drop and Withdrawal Deadlines": "Drop: 2025/01/17&#xa;Withdrawal: 2025/03/07"
  },
  {
    "Course Section": "CPEN_V 212-L2A - Computing Systems II",
    "Instructional Format": "Laboratory",
    "Section Status": "Waitlist",
    "Delivery Mode": "In Person Learning",
    "Drop and Withdrawal Deadlines": "Drop: 2025/01/17&#xa;Withdrawal: 2025/03/07"
  },
  {
    "Course Section": "CPEN_V 212-L2B - Computing Systems II",
    "Instructional Format": "Laboratory",
    "Section Status": "Closed",
    "Delivery Mode": "In Person Learning",
    "Drop and Withdrawal Deadlines": "Drop: 2025/01/17&#xa;Withdrawal: 2025/03/07"
  },
  {
    "Course Section": "CPEN_V 212-L2C - Computing Systems II",
    "Instructional Format": "Laboratory",
    "Section Status": "Open",
    "Delivery Mode": "In Person Learning",
    "Drop and Withdrawal Deadlines": "Drop: 2025/01/17&#xa;Withdrawal: 2025/03/07"
  },
  {
    "Course Section": "CPSC_V 203-201 - Programming, Problem Solving, and Algorithms",
    "Instructional Format": "Lecture",
    "Section Status": "Open",
    "Delivery Mode": "In Person Learning",
    "Course Section Definition Public Notes": "Due to unfixable technical issues, Workday Student is unable to manage the labs for CPSC 203. Therefore registration in the CPSC 203 lecture section is contingent on availability for an appropriate lab section and space in the lab. Please see the list below for details on when and where labs are expected at. The course staff will work with students to find a suitable lab time in the first week of classes. Students who cannot find a suitable lab time will unfortunately need to be de-registered from the course\n \nCPSC 203.L2A | Tue | 12:30 – 4 PM | ICCS X351\nCPSC 203.L2B | Mon | 12PM – 1:30PM | ICCS X351\nCPSC 203. L2C | Tue | 5PM – 6:30 PM | ICCS X350\nCPSC 203.L2D | Tue | 4 PM – 5:30 PM | ICCS X351\nCPSC 203.L2E | Tue | 5:30 PM – 7:00 PM | ICCS X351",
    "Drop and Withdrawal Deadlines": "Drop: 2025/01/17&#xa;Withdrawal: 2025/03/07"
  },
  {
    "Course Section": "CPSC_V 210-201 - Software Construction",
    "Instructional Format": "Lecture",
    "Section Status": "Open",
    "Delivery Mode": "In Person Learning",
    "Drop and Withdrawal Deadlines": "Drop: 2025/01/17&#xa;Withdrawal: 2025/03/07"
  },
  {
    "Course Section": "CPSC_V 210-202 - Software Construction",
    "Instructional Format": "Lecture",
    "Section Status": "Open",
    "Delivery Mode": "In Person Learning",
    "Drop and Withdrawal Deadlines": "Drop: 2025/01/17&#xa;Withdrawal: 2025/03/07"
  },
  {
    "Course Section": "CPSC_V 210-203 - Software Construction",
    "Instructional Format": "Lecture",
    "Section Status": "Waitlist",
    "Delivery Mode": "In Person Learning",
    "Drop and Withdrawal Deadlines": "Drop: 2025/01/17&#xa;Withdrawal: 2025/03/07"
  },
  {
    "Course Section": "CPSC_V 210-L2A - Software Construction",
    "Instructional Format": "Laboratory",
    "Section Status": "Open",
    "Delivery Mode": "In Person Learning",
    "Drop and Withdrawal Deadlines": "Drop: 2025/01/17&#xa;Withdrawal: 2025/03/07"
  },
  {
    "Course Section": "CPSC_V 210-L2B - Software Construction",
    "Instructional Format": "Laboratory",
    "Section Status": "Closed",
    "Delivery Mode": "In Person Learning",
    "Drop and Withdrawal Deadlines": "Drop: 2025/01/17&#xa;Withdrawal: 2025/03/07"
  },
  {
    "Course Section": "CPSC_V 210-L2C - Software Construction",
    "Instructional Format": "Laboratory",
    "Section Status": "Closed",
    "Delivery Mode": "In Person Learning",
    "Drop and Withdrawal Deadlines": "Drop: 2025/01/17&#xa;Withdrawal: 2025/03/07"
  },
  {
    "Course Section": "CPSC_V 210-L2D - Software Construction",
    "Instructional Format": "Laboratory",
    "Section Status": "Closed",
    "Delivery Mode": "In Person Learning",
    "Drop and Withdrawal Deadlines": "Drop: 2025/01/17&#xa;Withdrawal: 2025/03/07"
  },
  {
    "Course Section": "CPSC_V 210-L2E - Software Construction",
    "Instructional Format": "Laboratory",
    "Section Status": "Open",
    "Delivery Mode": "In Person Learning",
    "Drop and Withdrawal Deadlines": "Drop: 2025/01/17&#xa;Withdrawal: 2025/03/07"
  },
  {
    "Course Section": "CPSC_V 210-L2F - Software Construction",
    "Instructional Format": "Laboratory",
    "Section Status": "Open",
    "Delivery Mode": "In Person Learning",
    "Drop and Withdrawal Deadlines": "Drop: 2025/01/17&#xa;Withdrawal: 2025/03/07"
  },
  {
    "Course Section": "CPSC_V 210-L2G - Software Construction",
    "Instructional Format": "Laboratory",
    "Section Status": "Open",
    "Delivery Mode": "In Person Learning",
    "Drop and Withdrawal Deadlines": "Drop: 2025/01/17&#xa;Withdrawal: 2025/03/07"
  },
  {
    "Course Section": "CPSC_V 210-L2H - Software Construction",
    "Instructional Format": "Laboratory",
    "Section Status": "Open",
    "Delivery Mode": "In Person Learning",
    "Drop and Withdrawal Deadlines": "Drop: 2025/01/17&#xa;Withdrawal: 2025/03/07"
  },
  {
    "Course Section": "CPSC_V 210-L2J - Software Construction",
    "Instructional Format": "Laboratory",
    "Section Status": "Closed",
    "Delivery Mode": "In Person Learning",
    "Drop and Withdrawal Deadlines": "Drop: 2025/01/17&#xa;Withdrawal: 2025/03/07"
  },
  {
    "Course Section": "CPSC_V 210-L2K - Software Construction",
    "Instructional Format": "Laboratory",
    "Section Status": "Closed",
    "Delivery Mode": "In Person Learning",
    "Drop and Withdrawal Deadlines": "Drop: 2025/01/17&#xa;Withdrawal: 2025/03/07"
  },
  {
    "Course Section": "CPSC_V 210-L2L - Software Construction",
    "Instructional Format": "Laboratory",
    "Section Status": "Closed",
    "Delivery Mode": "In Person Learning",
    "Drop and Withdrawal Deadlines": "Drop: 2025/01/17&#xa;Withdrawal: 2025/03/07"
  },
  {
    "Course Section": "CPSC_V 210-L2M - Software Construction",
    "Instructional Format": "Laboratory",
    "Section Status": "Closed",
    "Delivery Mode": "In Person Learning",
    "Drop and Withdrawal Deadlines": "Drop: 2025/01/17&#xa;Withdrawal: 2025/03/07"
  },
  {
    "Course Section": "CPSC_V 210-L2N - Software Construction",
    "Instructional Format": "Laboratory",
    "Section Status": "Closed",
    "Delivery Mode": "In Person Learning",
    "Drop and Withdrawal Deadlines": "Drop: 2025/01/17&#xa;Withdrawal: 2025/03/07"
  },
  {
    "Course Section": "CPSC_V 210-L2P - Software Construction",
    "Instructional Format": "Laboratory",
    "Section Status": "Open",
    "Delivery Mode": "In Person Learning",
    "Drop and Withdrawal Deadlines": "Drop: 2025/01/17&#xa;Withdrawal: 2025/03/07"
  },
  {
    "Course Section": "CPSC_V 210-L2Q - Software Construction",
    "Instructional Format": "Laboratory",
    "Section Status": "Open",
    "Delivery Mode": "In Person Learning",
    "Drop and Withdrawal Deadlines": "Drop: 2025/01/17&#xa;Withdrawal: 2025/03/07"
  },
  {
    "Course Section": "CPSC_V 210-L2R - Software Construction",
    "Instructional Format": "Laboratory",
    "Section Status": "Open",
    "Delivery Mode": "In Person Learning",
    "Drop and Withdrawal Deadlines": "Drop: 2025/01/17&#xa;Withdrawal: 2025/03/07"
  },
  {
    "Course Section": "CPSC_V 210-L2S - Software Construction",
    "Instructional Format": "Laboratory",
    "Section Status": "Open",
    "Delivery Mode": "In Person Learning",
    "Drop and Withdrawal Deadlines": "Drop: 2025/01/17&#xa;Withdrawal: 2025/03/07"
  },
  {
    "Course Section": "CPSC_V 210-L2T - Software Construction",
    "Instructional Format": "Laboratory",
    "Section Status": "Open",
    "Delivery Mode": "In Person Learning",
    "Drop and Withdrawal Deadlines": "Drop: 2025/01/17&#xa;Withdrawal: 2025/03/07"
  },
  {
    "Course Section": "CPSC_V 210-L2U - Software Construction",
    "Instructional Format": "Laboratory",
    "Section Status": "Closed",
    "Delivery Mode": "In Person Learning",
    "Drop and Withdrawal Deadlines": "Drop: 2025/01/17&#xa;Withdrawal: 2025/03/07"
  },
  {
    "Course Section": "CPSC_V 210-L2V - Software Construction",
    "Instructional Format": "Laboratory",
    "Section Status": "Closed",
    "Delivery Mode": "In Person Learning",
    "Drop and Withdrawal Deadlines": "Drop: 2025/01/17&#xa;Withdrawal: 2025/03/07"
  },
  {
    "Course Section": "CPSC_V 210-L2X - Software Construction",
    "Instructional Format": "Laboratory",
    "Section Status": "Closed",
    "Delivery Mode": "In Person Learning",
    "Drop and Withdrawal Deadlines": "Drop: 2025/01/17&#xa;Withdrawal: 2025/03/07"
  },
  {
    "Course Section": "CPSC_V 210-L2Y - Software Construction",
    "Instructional Format": "Laboratory",
    "Section Status": "Closed",
    "Delivery Mode": "In Person Learning",
    "Drop and Withdrawal Deadlines": "Drop: 2025/01/17&#xa;Withdrawal: 2025/03/07"
  },
  {
    "Course Section": "CPSC_V 213-203 - Introduction to Computer Systems",
    "Instructional Format": "Lecture",
    "Section Status": "Waitlist",
    "Delivery Mode": "In Person Learning",
    "Drop and Withdrawal Deadlines": "Drop: 2025/01/17&#xa;Withdrawal: 2025/03/07"
  }
]